Workbook

Sheet Quotation 
A2: QUOTATION
C3: DATE : 6th -Jul,2025
A5: Customer Name : | B5: Ms
A6: Customer Contacts : | B6: +2567
A7: Customer Email : | B7: N/A
A9: Stock No. :
A10: Make :
A11: Chassis No. : | B11: NKE165-8016821
A12: Color : | B12: SILVER
A13: Engine Size / Fuel type : | B13: 1490 | C13: C.C | D13: Petrol (Hybrid)
A14: Year : | B14: 2015
A18: FIRST INSTALLMENT
B20: COST IN USD | C20: USD RATE | D20: COST IN Ugx
A21: C&F Mombasa | C21: 3570 | D21: =B21*C21 -> 0
A22: Clearance Mombasa-Kampala | C22: 3570 | D22: =B22*C22 -> 0
A23: C&F Kampala | D23: =B23*C23 -> 0
A24: TT Charges | B24: 40 | C24: 3570 | D24: =B24*C24 -> 142800
B25: =B21+B23+B24 -> 40 | C25: Total (C&F Kampala) | D25: =D21+D23+D22+D24 -> 142800
A27: SECOND INSTALLMENT
A29: Taxes Payable to URA | D29: ='with surcharge'!B17 -> 1553000
A30: Number plates | D30: 714300
A31: 3rd Party Insurance
A32: Agent fees | D32: 400000
A36: REGISTRATION PROCESS | D36: =SUM(D29:D35) -> 2667300
A38: GRAND TOTAL (UGX) | D38: =D25+D36 -> 2810100
A39: GRAND TOTAL (UGX)
A41: Bank information
A43: Payee: NSB BUSINESS SOLUTIONS (U) LTD
A45: Bank Name: EQUITY BANK.
A47: Bank address: EQUITY BANK ,CHURCH HOUSE
A48: SWIFT CODE: EQBLUGKA
A50: Account No: Ugx: 1001202951908
A51: USD: 1001203004471

Sheet with surcharge
A1: MV CALCULATOR | D1: 4 tonne trucks 20% surcharge
A2: MV CALCULATOR | D2: double cabins and single cabin 20% surcharge
A3: EXCHANGE RATE | B3: 3586.8768 | D3: 4 tonne trucks pays 10% Import duty
A4: YEAR | B4: 2010 | D4: Ordinary cars pay 25% import duty
A5: CIF USD | D5: 3tonne< Trucks pay 20% Import duty
A6: CUSTOMS VALUE | B6: =+B5*B3 -> 0 | D6: Above 20,000 kgs Gross weight Pay No Iimport Duty
A8: IMPORT DECLARATION FEES | B8: =B6*1% -> 0 | D8: All trucks pay 20% Surcharge
A9: IMPORT DUTY | B9: =25%*B6 -> 0
A10: V.A.T | B10: =(B9+B6)*18% -> 0
A11: W.H.T | B11: =6%*B6 -> 0
A12: SURCHARGE (ENVIRONMENTAL) | B12: =50%*B6 -> 0
A13: REG FEES | B13: 1500000
A14: STAMP DUTY | B14: 18000
A15: REG FORM | B15: 35000
A16: INFRASTRUCTURAL LEVY | B16: =1.5%*B6 -> 0
A17: TOTAL TAXES | B17: =SUM(B8:B16) -> 1553000

Sheet without Surcharge
A1: MV CALCULATOR | D1: 4 tonne trucks 20% surcharge
A2: MV CALCULATOR | D2: double cabins and single cabin 20% surcharge
A3: EXCHANGE RATE | B3: ='with surcharge'!B3 -> 3586.8768 | D3: 4 tonne trucks pays 10% Import duty
A4: YEAR | B4: 2017 | D4: Ordinary cars pay 25% import duty
A5: CIF USD | D5: 3tonne< Trucks pay 20% Import duty
A6: CUSTOMS VALUE | B6: =+B5*B3 -> 0 | D6: Above 20,000 kgs Gross weight Pay No Iimport Duty
D7: All trucks pay 20% Surcharge
A8: IMPORT DECLARATION FEES | B8: =B6*1% -> 0
A9: IMPORT DUTY | B9: =25%*B6 -> 0
A10: V.A.T | B10: =(B9+B6)*18% -> 0
A11: W.H.T | B11: =6%*B6 -> 0
A12: SURCHARGE (ENVIRONMENTAL)
A13: REG FEES | B13: 1500000
A14: STAMP DUTY | B14: 18000
A15: REG FORM | B15: 35000
A16: INFRASTRUCTURAL LEVY | B16: =1.5%*B6 -> 0
A17: TOTAL TAXES | B17: =SUM(B8:B16) -> 1553000

Sheet Trucks & Cabins
A1: MV CALCULATOR | D1: 4 tonne trucks 20% surcharge
D2: double cabins and single cabin 20% surcharge
A3: EXCHANGE RATE | B3: ='without Surcharge'!B3 -> 3586.8768 | D3: 4 tonne trucks pays 10% Import duty
A4: YEAR | D4: Ordinary cars pay 25% import duty
A5: CIF USD | B5: 4975.08 | D5: 3tonne< Trucks pay 20% Import duty
A6: CUSTOMS VALUE | B6: =+B5*B3 -> 17844999 | D6: Above 20,000 kgs Gross weight Pay No Iimport Duty
D7: All trucks pay 20% Surcharge
A8: IMPORT DUTY | B8: =25%*B6 -> 4461249.8
A9: V.A.T | B9: =(B8+B6)*18% -> 4015124.8
A10: W.H.T | B10: =6%*B6 -> 1070699.9
A11: ENVIRONMENTAL LEVY (SURCHARGE) | B11: =20%*B6 -> 3568999.8
A12: MOTOR VEHICLE REG FEES | B12: 1500000
A13: STAMP DUTY ON VEHICLE IMPORTS | B13: 18000
A14: MOTOR VEHICLE FORM FEES | B14: 35000
A15: INFRASTRUCTURE LEVY | B15: =1.5%*B6 -> 267674.99
A16: TOTAL TAXES | B16: =SUM(B8:B15) -> 14936749

Sheet 7 TONNE TRUCKS
A1: MV CALCULATOR- TRUCKS 7 > 19.9 TONNES
A3: EXCHANGE RATE | B3: ='Trucks & Cabins'!B3 -> 3586.8768
A4: YEAR | B4: 2005
A5: CIF USD
A6: CUSTOMS VALUE | B6: =+B5*B3 -> 0
A8: IMPORT DUTY | B8: =10%*B6 -> 0
A9: V.A.T | B9: =(B8+B6)*18% -> 0
A10: W.H.T | B10: =6%*B6 -> 0
A11: ENVIRONMENTAL LEVY (SURCHARGE) | B11: =20%*B6 -> 0
A12: MOTOR VEHICLE REG FEES | B12: 1250000
A13: STAMP DUTY ON VEHICLE IMPORTS | B13: 18000
A14: MOTOR VEHICLE FORM FEES | B14: 35000
A15: INFRASTRUCTURE LEVY | B15: =1.5%*B6 -> 0
A16: TOTAL TAXES | B16: =SUM(B8:B15) -> 1303000

Sheet TRACTOR HEADS AND 20>
A1: MV CALCULATOR- TRUCKS 7 > 19.9 TONNES
A3: EXCHANGE RATE | B3: ='7 TONNE TRUCKS'!B3 -> 3586.8768
A4: YEAR | B4: 2004
A5: CIF USD | B5: 28063
A6: CUSTOMS VALUE | B6: =+B5*B3 -> 1.0065852e+08
A8: IMPORT DUTY | B8: =0%*B6 -> 0
A9: V.A.T | B9: =(B8+B6)*18% -> 18118534
A10: W.H.T | B10: =6%*B6 -> 6039511.4
A11: ENVIRONMENTAL LEVY (SURCHARGE) | B11: =20%*B6 -> 20131705
A12: MOTOR VEHICLE REG FEES | B12: 1250000
A13: STAMP DUTY ON VEHICLE IMPORTS | B13: 18000
A14: MOTOR VEHICLE FORM FEES | B14: 35000
A15: INFRASTRUCTURE LEVY | B15: =0%*B6 -> 0
A16: TOTAL TAXES | B16: =SUM(B8:B15) -> 45592750
